{
  "main": {
    "name":"Frank Norbert Mbah",
    "description":"I am a fullstack web/Blockchain Engineer, a Computer scientist, and Tech enthusiast. I develop rigidly funcntional and responsive sites with React, Redux, Express, Nodejs, MongodB, sql. I Develop Dapps with flawless connection and transaction with and to the Ethereum blochain, with solidity and Web3js/Ethers ",
    "image":"profilepic.jpg",
    "bio":"I am a hands-on Fullstack Web and Blockchain(web3) Engineer, quite eager to collaborate with customers to find optimal solutions, I carefully customize projects to user needs and budgets, I provide reliably actionable code and software assets for customers, that can be deployed in the cloud like aws, heroku, digital ocean and more, I love to work with teams or groups of Developers and i get along quite nicely, i learn any stack or trend with rigid mastery in a very short period of time.",
    "contactmessage":"Ring me up through my email, or call am always available",
    "email": "norbertmbafrank@gmail.com",
    "phone": "+2347025488825",
    "github":"https://github.com/NorVirae",
    "project":"https://github.com/NorVirae",
    "address":{
      "street":"New haven",
      "city":"Enugu Town",
      "state":"Enugu",
      "zip": "234001"
    },
    "website": "https://www.tadaflux.io",
    "resumedownload":"https://www.github.com/NorVirae",
    "social":[
      {
        "name":"facebook",
        "url":"https://web.facebook.com/mbafrank.norbert/",
        "className":"fa fa-facebook"
      },
      {
        "name":"twitter",
        "url":"http://twitter.com/DrBooOfficial",
        "className":"fa fa-twitter"
      },
      {
        "name":"linkedin",
        "url":"https://www.linkedin.com/in/norbert-mba-440b2117b",
        "className":"fa fa-linkedin"
      },
      {
        "name":"instagram",
        "url":"https://www.instagram.com/doctor_boo/",
        "className":"fa fa-instagram"
      },
      {
        "name":"github",
        "url":"https://github.com/NorVirae",
        "className":"fa fa-github"
      }
    ]
  },
  "resume":{
    "skillmessage":"I am a Full stack Javascript Developer with the latest and most secure technologies and framework, Nodejs, React, Express, MongoDB, I can also create, manage and deploy your projects on various cloud services like AWS with amplify, Digital ocean droplets, firebase projects, Heroku and more, I love to work with teams or groups of Developers and i get along quite nicely, i learn any stack in a very short period of time",
    "education":[
      {
        "school":"Madonna University",
        "degree":"Bsc in Computer science",
        "graduated":"October 2021",
        "description":"The university was quite resouceful for me imbibed me with the problem solving skills i quite efficiently possess today."
      }
    ],
    "work":[
      {
        "company":"Quiva Games",
        "title":"Web developer",
        "years":"November 2021 - present",
        "description":"worked with a team of Game developers to Develop Blockchain Dapps and Webapps for Blockchain games"
      },
      {
        "company":"Fischela",
        "title":"Founder/CEO/Web developer",
        "years":"december 2020 - present",
        "description":"Worked with a team of Developers to build both frontend and backend for a food Delivery system, integrated payment system"
      },
      {
        "company":"Liqair Studios",
        "title":"Frontend Developer",
        "years":"February 2022 - present",
        "description":"Maintained web apps and added new features"
      },
      {
        "company":"nHub Nigeria",
        "title":"Fullstack Web Developer/Intern",
        "years":"february 2019 - October 2020",
        "description":"Developed software for both mobile and Desktop environment."
      }
      
    ],
    "skills":[
      {
        "name":"solidity",
        "level":"70%"
      },
      {
        "name":"Nodejs",
        "level":"80%"
      },
      {
        "name":"Javascript",
        "level":"80%"
      },
      {
        "name":"Typescript",
        "level":"70%"
      },
      {
        "name":"Web3js & Ethers",
        "level":"79%"
      }, 
      {
        "name":"ReactJs",
        "level":"98%"
      },
      {
        "name":"CSS",
        "level":"60%"
      },
      
      {
        "name":"MongoDb",
        "level":"90%"
      },
      {
        "name":"Sql",
        "level":"90%"
      },
      {
        "name":"aws",
        "level":"50%"
      },
      {
        "name":"Digital Ocean",
        "level":"50%"
      },
      {
        "name":"Heroku",
        "level":"50%"
      },
      {
        "name":"Git",
        "level":"80%"
      }
    ]
  },
  "portfolio":{
    "projects": [
      {
        "title":"Fischela",
        "category":"An Ecommerce Online shop",
        "image":"fischela.jpg",
        "url":"https://www.fischela.com"
      },

      {
        "title":"Liqair Studios",
        "category":"An Ecommerce Online shop",
        "image":"liqair.png",
        "url":"https://www.liqair.art"
      },
      {
        "title":"Portfolio site",
        "category":"A React based portfolio website for me",
        "image":"04.png",
        "url":"https://norbertmbafrank.netlify.app"
      },

      {
        "title":"Cloud Service System - upload large files, stream track files(checkout the cool project on github)",
        "category":"An Ecommerce Online shop",
        "image":"clouds.png",
        "url":"https://github.com/NorVirae/cloudservice-upload-track-stream.git"
      },

     
      {
        "title":"Blochain Wallet with custom Token",
        "category":"An Ecommerce Online shop",
        "image":"wallet.png",
        "url":"https://github.com/NorVirae/fadrPay.git"
      },

      {
        "title":"A payment system with paystack by stripe",
        "category":"An Ecommerce Online shop",
        "image":"paystack.png",
        "url":"https://paystack-pay-demo.netlify.app/"
      },
      {
        "title":"nHub blogger",
        "category":"A blog web app i team worked with my fellow interns at nHub",
        "image":"03.png",
        "url":"https://nhubfoundation.org/blog/"
      }
      
    ]
  }
}
